pip_start/__init__.py
pip_start/pip_start.py
pip_start-0.1.3.dist-info/LICENSE
pip_start-0.1.3.dist-info/METADATA
pip_start-0.1.3.dist-info/WHEEL
pip_start-0.1.3.dist-info/top_level.txt
pip_start-0.1.3.dist-info/RECORD
