Metadata-Version: 2.1
Name: pip_start
Version: 0.1.3
Summary: A Python Package allowing thr automatic checking and updating of a python package upon import
Home-page: https://github.com/Veillax/pip_start
Author: Veillax
Author-email: contact@veillax.com
Classifier: Programming Language :: Python :: 3
Classifier: License :: OSI Approved :: GNU Affero General Public License v3
Classifier: Operating System :: OS Independent
Requires-Python: >=3.9
License-File: LICENSE
Requires-Dist: requests
